{"assets/Fonts/Aquatico.otf":["assets/Fonts/Aquatico.otf"],"assets/Icons/Department.png":["assets/Icons/Department.png"],"assets/Icons/Profile.png":["assets/Icons/Profile.png"],"assets/Icons/SignOut.png":["assets/Icons/SignOut.png"],"assets/Images/Botany.png":["assets/Images/Botany.png"],"assets/Images/Login_logo.png":["assets/Images/Login_logo.png"],"assets/Images/excel.png":["assets/Images/excel.png"],"packages/cupertino_icons/assets/CupertinoIcons.ttf":["packages/cupertino_icons/assets/CupertinoIcons.ttf"]}